README.rst
setup.py
baguette_utils.egg-info/PKG-INFO
baguette_utils.egg-info/SOURCES.txt
baguette_utils.egg-info/dependency_links.txt
baguette_utils.egg-info/requires.txt
baguette_utils.egg-info/top_level.txt
sel/__init__.py
sel/request.py
sel/serializers.py