Metadata-Version: 1.1
Name: baguette-utils
Version: 0.14
Summary: some dummy wrappers
Home-page: https://github.com/baguette-io/baguette-utils/
Author: pydavid
Author-email: pydavid@baguette.io
License: UNKNOWN
Keywords: utils,request
Platform: Linux/UNIX
Platform: MacOS
Platform: Windows
Classifier: Programming Language :: Python
Classifier: Programming Language :: Python :: 2.7
Classifier: Programming Language :: Python :: 3.6
Classifier: License :: OSI Approved
Classifier: License :: OSI Approved :: GNU Lesser General Public License v3 (LGPLv3)
Classifier: Operating System :: OS Independent
